wakeypy/__init__.py
wakeypy/functions.py
wakeypy/main.py
wakeypy/text_print.py
wakeypy-0.1.2.dist-info/METADATA
wakeypy-0.1.2.dist-info/WHEEL
wakeypy-0.1.2.dist-info/entry_points.txt
wakeypy-0.1.2.dist-info/RECORD
