Metadata-Version: 2.4
Name: wakeypy
Version: 0.1.2
Summary: Add your description here
Author-email: Evan Baird <evanbaird@evans-mbp.lan>
Requires-Python: >=3.12
Requires-Dist: art>=6.4
Requires-Dist: httpx>=0.28.1
Requires-Dist: tomli>=2.2.1
Requires-Dist: typer>=0.15.1
Requires-Dist: wakepy>=0.10.1
